dataparserlib/__init__.py
dataparserlib/dictionary.py
DataParserLib-0.0.0.5.dist-info/LICENSE
DataParserLib-0.0.0.5.dist-info/METADATA
DataParserLib-0.0.0.5.dist-info/WHEEL
DataParserLib-0.0.0.5.dist-info/top_level.txt
DataParserLib-0.0.0.5.dist-info/RECORD
