Metadata-Version: 2.1
Name: DataParserLib
Version: 0.0.0.5
Summary: A python data parsing library intended to parse dictionaries, lists, and other common structured data
Home-page: https://github.com/AUCR/DataParserLib
Author: Wyatt Roersma
Author-email: wyatt@aucr.io
License: Apache-2.0
Platform: UNKNOWN
Classifier: Development Status :: 4 - Beta
Classifier: Intended Audience :: Developers
Classifier: License :: OSI Approved :: Apache Software License
Classifier: Programming Language :: Python :: 3.6
